datasetinsights/__init__.py
datasetinsights/__main__.py
datasetinsights/commands/__init__.py
datasetinsights/commands/convert.py
datasetinsights/commands/download.py
datasetinsights/constants.py
datasetinsights/dashboard.py
datasetinsights/datasets/__init__.py
datasetinsights/datasets/exceptions.py
datasetinsights/datasets/synthetic.py
datasetinsights/datasets/transformers/__init__.py
datasetinsights/datasets/transformers/base.py
datasetinsights/datasets/transformers/coco.py
datasetinsights/datasets/unity_perception/__init__.py
datasetinsights/datasets/unity_perception/captures.py
datasetinsights/datasets/unity_perception/exceptions.py
datasetinsights/datasets/unity_perception/metrics.py
datasetinsights/datasets/unity_perception/references.py
datasetinsights/datasets/unity_perception/tables.py
datasetinsights/datasets/unity_perception/validation.py
datasetinsights/io/__init__.py
datasetinsights/io/bbox.py
datasetinsights/io/download.py
datasetinsights/io/downloader/__init__.py
datasetinsights/io/downloader/base.py
datasetinsights/io/downloader/gcs_downloader.py
datasetinsights/io/downloader/http_downloader.py
datasetinsights/io/exceptions.py
datasetinsights/io/gcs.py
datasetinsights/stats/__init__.py
datasetinsights/stats/image_analysis/__init__.py
datasetinsights/stats/image_analysis/laplacian.py
datasetinsights/stats/image_analysis/spectral_analysis.py
datasetinsights/stats/statistics.py
datasetinsights/stats/visualization/__init__.py
datasetinsights/stats/visualization/app.py
datasetinsights/stats/visualization/bbox2d_plot.py
datasetinsights/stats/visualization/bbox3d_plot.py
datasetinsights/stats/visualization/constants.py
datasetinsights/stats/visualization/font/DroidSansFallback.ttf
datasetinsights/stats/visualization/font/LICENSE-2.0.txt
datasetinsights/stats/visualization/keypoints_plot.py
datasetinsights/stats/visualization/keypoints_pose.py
datasetinsights/stats/visualization/object_detection.py
datasetinsights/stats/visualization/overview.py
datasetinsights-1.1.2.dist-info/entry_points.txt
datasetinsights-1.1.2.dist-info/WHEEL
datasetinsights-1.1.2.dist-info/METADATA
datasetinsights-1.1.2.dist-info/RECORD
