Metadata-Version: 2.1
Name: datasetinsights
Version: 1.1.2
Summary: Synthetic dataset insights.
Home-page: https://github.com/Unity-Technologies/datasetinsights
License: Apache-2.0
Author: Unity AI Perception Team
Author-email: computer-vision@unity3d.com
Requires-Python: >=3.8,<3.11
Classifier: Development Status :: 3 - Alpha
Classifier: Environment :: Console
Classifier: Framework :: Jupyter
Classifier: License :: OSI Approved :: Apache Software License
Classifier: Operating System :: OS Independent
Classifier: Programming Language :: Python :: 3
Classifier: Programming Language :: Python :: 3.10
Classifier: Programming Language :: Python :: 3.8
Classifier: Programming Language :: Python :: 3.9
Classifier: Topic :: Scientific/Engineering :: Artificial Intelligence
Classifier: Topic :: Scientific/Engineering :: Visualization
Classifier: Topic :: Software Development :: Libraries :: Python Modules
Classifier: Topic :: Utilities
Requires-Dist: click (==8.0.4)
Requires-Dist: codetiming (>=1.2.0,<2.0.0)
Requires-Dist: cython (>=0.29.14,<0.30.0)
Requires-Dist: dash (>=2.3.1,<3.0.0)
Requires-Dist: dask[complete] (>=2.14.0,<3.0.0)
Requires-Dist: google-cloud-storage (>=1.24.1,<2.0.0)
Requires-Dist: matplotlib (>=3.3.1,<4.0.0)
Requires-Dist: numpy (>=1.17,<2.0)
Requires-Dist: opencv-python (>=4.4.0.42,<5.0.0.0)
Requires-Dist: pandas (>=1.0.1,<2.0.0)
Requires-Dist: plotly (>=5.0.0)
Requires-Dist: pyquaternion (>=0.9.5,<0.10.0)
Requires-Dist: scipy (>=1.8.0,<2.0.0)
Requires-Dist: tqdm (>=4.45.0,<5.0.0)
Project-URL: Documentation, https://datasetinsights.readthedocs.io/en/latest/
Project-URL: Repository, https://github.com/Unity-Technologies/datasetinsights
